data_inclusion/schema/__init__.py
data_inclusion/schema/base.py
data_inclusion/schema/common.py
data_inclusion/schema/helpers.py
data_inclusion/schema/validation.py
data_inclusion/schema/v0/__init__.py
data_inclusion/schema/v0/frais.py
data_inclusion/schema/v0/labels_nationaux.py
data_inclusion/schema/v0/modes_accueil.py
data_inclusion/schema/v0/modes_orientation.py
data_inclusion/schema/v0/profils.py
data_inclusion/schema/v0/score_qualite.py
data_inclusion/schema/v0/services.py
data_inclusion/schema/v0/structures.py
data_inclusion/schema/v0/thematiques.py
data_inclusion/schema/v0/typologies_de_services.py
data_inclusion/schema/v0/typologies_de_structures.py
data_inclusion/schema/v0/zones_de_diffusion.py
data_inclusion/schema/v1/__init__.py
data_inclusion/schema/v1/frais.py
data_inclusion/schema/v1/modes_accueil.py
data_inclusion/schema/v1/modes_mobilisation.py
data_inclusion/schema/v1/publics.py
data_inclusion/schema/v1/reseaux_porteurs.py
data_inclusion/schema/v1/score_qualite.py
data_inclusion/schema/v1/services.py
data_inclusion/schema/v1/structures.py
data_inclusion/schema/v1/thematiques.py
data_inclusion/schema/v1/types_de_services.py
data_inclusion_schema-1.0.5.dist-info/licenses/LICENSE.md
data_inclusion_schema-1.0.5.dist-info/WHEEL
data_inclusion_schema-1.0.5.dist-info/METADATA
data_inclusion_schema-1.0.5.dist-info/RECORD
