Metadata-Version: 2.4
Name: data-inclusion-schema
Version: 1.0.5
Summary: Schéma de l'offre d'insertion
Author-email: data⋅inclusion <data-inclusion@inclusion.gouv.fr>
Requires-Python: >=3.10
Classifier: Programming Language :: Python
Classifier: Programming Language :: Python :: 3
License-File: LICENSE.md
Requires-Dist: pydantic[email]>=2.1.1,<3.0.0
Requires-Dist: pendulum~=3.0
Project-URL: Home, https://data.inclusion.gouv.fr
Project-URL: Source, https://github.com/gip-inclusion/data-inclusion-schema
